seagal/__init__.py
seagal/_gmod.py
seagal/_plotting.py
seagal/_utils.py
seagal/lee_vec.py
seagal/seagal.py
seagal/spatial_measure.py
seagal/modules/__init__.py
seagal/modules/gmod.py
seagal-2.5.2.dist-info/LICENSE
seagal-2.5.2.dist-info/METADATA
seagal-2.5.2.dist-info/WHEEL
seagal-2.5.2.dist-info/top_level.txt
seagal-2.5.2.dist-info/RECORD
