Metadata-Version: 2.1
Name: seagal
Version: 2.5.2
Summary: Spatial Enrichment Analysis of Gene Association using L-index
Home-page: https://github.com/linhuawang/SEAGAL
Author: Linhua Wang
Author-email: linhua.wang1994@gmail.com
License: MIT
Classifier: Programming Language :: Python :: 3
Classifier: License :: OSI Approved :: MIT License
License-File: LICENSE
Requires-Dist: scanpy[leiden]
Requires-Dist: numpy
Requires-Dist: anndata
Requires-Dist: pandas
Requires-Dist: matplotlib
Requires-Dist: seaborn
Requires-Dist: scipy
Requires-Dist: squidpy
Requires-Dist: scikit-learn
Requires-Dist: libpysal
Requires-Dist: statsmodels
